delpy/__init__.py
delpy/_toolbox.xml
delpy/capture.py
delpy/delpy.py
delpy/static/delpy_block.js
delpy/static/delpy_blockly.js
delpy/static/delpy_javascript.js
delpy/static/delpy_python.js
delpy/static/index.js
delpy/static/lang.js
delpy/static/run.js
delpywidget-0.0.1.data/data/share/jupyter/nbextensions/delpy/delpy_block.js
delpywidget-0.0.1.data/data/share/jupyter/nbextensions/delpy/delpy_blockly.js
delpywidget-0.0.1.data/data/share/jupyter/nbextensions/delpy/delpy_javascript.js
delpywidget-0.0.1.data/data/share/jupyter/nbextensions/delpy/delpy_python.js
delpywidget-0.0.1.data/data/share/jupyter/nbextensions/delpy/index.js
delpywidget-0.0.1.data/data/share/jupyter/nbextensions/delpy/lang.js
delpywidget-0.0.1.data/data/share/jupyter/nbextensions/delpy/run.js
delpywidget-0.0.1.dist-info/LICENSE.md
delpywidget-0.0.1.dist-info/METADATA
delpywidget-0.0.1.dist-info/WHEEL
delpywidget-0.0.1.dist-info/top_level.txt
delpywidget-0.0.1.dist-info/RECORD
