Metadata-Version: 2.1
Name: delpywidget
Version: 0.0.1
Summary: Blockly w/ Python on Jupyter Notebook
Home-page: https://github.com/Edwauline/DelpyWidget
Author: Edwige Gros
Author-email: edwige.gros@laposte.net
License: MIT
Platform: UNKNOWN
Classifier: Development Status :: 3 - Alpha
Classifier: Programming Language :: Python :: 3
Classifier: Programming Language :: Python :: 3.6
Requires-Dist: jupyter
